sadface/__init__.py
sadface/__main__.py
sadface/aml.py
sadface/config.py
sadface/repl.py
sadface/sadface.py
sadface/validation.py
sadface/version.py
tests/__init__.py
tests/config_test.py
tests/core_test.py
tests/validation_test.py
sadface-0.5.3.1.dist-info/LICENSE
sadface-0.5.3.1.dist-info/METADATA
sadface-0.5.3.1.dist-info/WHEEL
sadface-0.5.3.1.dist-info/top_level.txt
sadface-0.5.3.1.dist-info/RECORD
