Metadata-Version: 2.1
Name: sadface
Version: 0.5.3.1
Summary: SADFace - The Simple Argument Description Format
Home-page: https://github.com/Open-Argumentation/SADFace.git
Author: Simon Wells
Author-email: mail@simonwells.org
License: UNKNOWN
Platform: UNKNOWN
